Workbook

Sheet Assumptions
A1: Frontier Intelligence — LLM cost assumptions
A3: Volume assumptions (per month)
A4: Параметр | B4: Значение | C4: Заметка
A5: Sources active | B5: 47 | C5: 31 RSS + 7 TG + 6 web + 3 api
A6: Posts per day (avg) | B6: 500 | C6: 31×8 RSS + 7×20 TG + ~50 web/api
A7: Posts per month | B7: =B6*30 -> 15000 | C7: B6 × 30 days
A8: Posts with images (vision) | B8: =B7*0.3 -> 4500 | C8: ~30% постов с картинками
A9: MCP synthesis calls / month | B9: 1500 | C9: ~50/день для Claude-проектов
A10: Missing-signal probes / month | B10: 600 | C10: ~20/день в worker
A12: Token budgets per call (из shared/config.py + .env.balanced)
A13: Задача | B13: Input tok | C13: Output tok | D13: Источник бюджета
A14: relevance_concepts (joint) | B14: 1800 | C14: 300 | D14: GIGACHAT_TOKEN_BUDGET_RELEVANCE_CONCEPTS
A15: relevance (split) | B15: 1500 | C15: 200 | D15: GIGACHAT_TOKEN_BUDGET_RELEVANCE
A16: concepts (split) | B16: 1500 | C16: 250 | D16: GIGACHAT_TOKEN_BUDGET_CONCEPTS
A17: valence | B17: 1200 | C17: 200 | D17: GIGACHAT_TOKEN_BUDGET_VALENCE
A18: embed (1 пост) | B18: 1200 | C18: 0 | D18: GIGACHAT_TOKEN_BUDGET_EMBED, EmbeddingsGigaR
A19: vision_prompt + image | B19: 2600 | C19: 400 | D19: 600 prompt + ~2000 image tokens
A20: mcp_synthesis | B20: 4000 | C20: 1500 | D20: frontier_brief / search_balanced
A21: missing_signals probe | B21: 5000 | C21: 1000 | D21: worker/services/missing_signals.py
A24: Расчётный объём токенов в месяц
A25: Поток | B25: Input M | C25: Output M | D25: Формула
A26: relevance+concepts | B26: =B7*B14/1000000 -> 27 | C26: =B7*C14/1000000 -> 4.5 | D26: posts/мес × budget
A27: valence | B27: =B7*B17/1000000 -> 18 | C27: =B7*C17/1000000 -> 3
A28: embed | B28: =B7*B18/1000000 -> 18 | C28: 0
A29: vision (постов с картинками) | B29: =B8*B19/1000000 -> 11.7 | C29: =B8*C19/1000000 -> 1.8
A30: mcp_synthesis | B30: =B9*B20/1000000 -> 6 | C30: =B9*C20/1000000 -> 2.25
A31: missing_signals | B31: =B10*B21/1000000 -> 3 | C31: =B10*C21/1000000 -> 0.6
A32: ИТОГО (M токенов) | B32: =SUM(B26:B31) -> 83.7 | C32: =SUM(C26:C31) -> 12.15

Sheet Tariffs
A1: Тарифы провайдеров (май 2026)
A3: Провайдер | B3: Модель | C3: Input ₽/1M | D3: Output ₽/1M | E3: Тип | F3: Заметка
A4: Wormsoft | B4: Simple plan (любые модели в кредитах) | C4: 0 | D4: 0 | E4: Подписка 1500₽/мес | F4: 500k кредитов / 5ч ≈ 72M кредитов/мес
A5: Wormsoft | B5: wormsoft/agent/medium (текст) | C5: 100 | D5: 200 | E5: Через подписку | F5: Эффективная цена внутри Simple
A6: Wormsoft | B6: qwen/qwen3-embedding:8b | C6: 50 | D6: 0 | E6: Через подписку | F6: Embedding endpoint /api/gpt/embedding
A7: GigaChat | B7: GigaChat-2-Lite | C7: 200 | D7: 200 | E7: Pay-as-you-go | F7: Sber для физлиц после Feb-2026
A8: GigaChat | B8: GigaChat-2-Pro | C8: 500 | D8: 500 | E8: Pay-as-you-go (3M за 1500₽) | F8: Используется для vision
A9: GigaChat | B9: GigaChat-2-Max | C9: 1500 | D9: 1500 | E9: Pay-as-you-go | F9: Не использовать в проде
A10: GigaChat | B10: EmbeddingsGigaR | C10: 50 | D10: 0 | E10: Pay-as-you-go | F10: 2560d, 4096 ctx
A11: Polza.ai | B11: GPT-4o Mini | C11: 13 | D11: 53 | E11: Pay-as-you-go | F11: Очень дёшево, без подписки
A12: Polza.ai | B12: Claude 4.5 Sonnet | C12: 264 | D12: 1318 | E12: Pay-as-you-go | F12: Дорого, только для премиум
A13: Polza.ai | B13: GigaChat-2 / Qwen | C13: 50 | D13: 100 | E13: Pay-as-you-go | F13: Маркап ~5-10%
A14: VseLLM | B14: минимальные модели | C14: 38 | D14: 50 | E14: Pay-as-you-go | F14: От 38₽/1M, ~10% ниже рынка
A15: VseLLM | B15: GigaChat-2-Max | C15: 650 | D15: 650 | E15: Pay-as-you-go | F15: Без VPN, в рублях
... A20: OpenRouter | B20: Платные модели | C20: 5 | D20: 15 | E20: Pay-as-you-go | F20: Когда free недоступен

Sheet Scenarios
A1: Сценарии стоимости (₽/месяц)
A3: Объёмы тянутся с листа Assumptions.
A5: Поток | B5: Input M | C5: Output M | D5: S0: As-is (Wormsoft+GigaPro) | E5: S1: GigaChat-only | F5: S2: Wormsoft+OR-free vision | G5: S3: Polza/VseLLM pay-as-you-go | H5: S4: Гибрид (рекомендуется)
A6: relevance+concepts | B6: =Assumptions!B26 -> 27 | C6: =Assumptions!C26 -> 4.5 | D6: =B6*0+C6*0 -> 0 | E6: =B6*200+C6*200 -> 6300 | F6: =B6*0+C6*0 -> 0 | G6: =B6*80+C6*120 -> 2700 | H6: =B6*0+C6*0 -> 0
A7: valence | B7: =Assumptions!B27 -> 18 | C7: =Assumptions!C27 -> 3 | D7: =B7*0+C7*0 -> 0 | E7: =B7*200+C7*200 -> 4200 | F7: =B7*0+C7*0 -> 0 | G7: =B7*80+C7*120 -> 1800 | H7: =B7*0+C7*0 -> 0
A8: embed | B8: =Assumptions!B28 -> 18 | C8: =Assumptions!C28 -> 0 | D8: =B8*0+C8*0 -> 0 | E8: =B8*50+C8*0 -> 900 | F8: =B8*0+C8*0 -> 0 | G8: =B8*50+C8*0 -> 900 | H8: =B8*0+C8*0 -> 0
A9: vision | B9: =Assumptions!B29 -> 11.7 | C9: =Assumptions!C29 -> 1.8 | D9: =B9*500+C9*500 -> 6750 | E9: =B9*500+C9*500 -> 6750 | F9: =B9*0+C9*0 -> 0 | G9: =B9*80+C9*200 -> 1296 | H9: =B9*150+C9*150 -> 2025
A10: mcp_synthesis | B10: =Assumptions!B30 -> 6 | C10: =Assumptions!C30 -> 2.25 | D10: =B10*0+C10*0 -> 0 | E10: =B10*500+C10*500 -> 4125 | F10: =B10*0+C10*0 -> 0 | G10: =B10*80+C10*120 -> 750 | H10: =B10*0+C10*0 -> 0
A11: missing_signals | B11: =Assumptions!B31 -> 3 | C11: =Assumptions!C31 -> 0.6 | D11: =B11*0+C11*0 -> 0 | E11: =B11*200+C11*200 -> 720 | F11: =B11*0+C11*0 -> 0 | G11: =B11*80+C11*120 -> 312 | H11: =B11*0+C11*0 -> 0
A12: Variable cost | D12: =SUM(D6:D11) -> 6750 | E12: =SUM(E6:E11) -> 22995 | F12: =SUM(F6:F11) -> 0 | G12: =SUM(G6:G11) -> 7758 | H12: =SUM(H6:H11) -> 2025
A13: Subscription / fixed (₽/мес) | D13: 1500 | E13: 0 | F13: 1500 | G13: 0 | H13: 1600
A15: ИТОГО ₽/мес | D15: =D12+D13 -> 8250 | E15: =E12+E13 -> 22995 | F15: =F12+F13 -> 1500 | G15: =G12+G13 -> 7758 | H15: =H12+H13 -> 3625
A16: ₽/день | D16: =D15/30 -> 275 | E16: =E15/30 -> 766.5 | F16: =F15/30 -> 50 | G16: =G15/30 -> 258.6 | H16: =H15/30 -> 120.83333
A17: % от текущего (S0) | D17: =D15/$D$15 -> 1 | E17: =E15/$D$15 -> 2.7872727 | F17: =F15/$D$15 -> 0.18181818 | G17: =G15/$D$15 -> 0.94036364 | H17: =H15/$D$15 -> 0.43939394
A19: Заметки
A20: S0 (As-is) — фактическая текущая конфигурация: Wormsoft Simple обслуживает основную текстовую обработку, GigaChat Pro используется для Vision (~2 пакета).
A21: S1 (GigaChat-only) — гипотетический максимум: всё на GigaChat. Показывает, сколько без подписки Wormsoft.
A22: S2 (Wormsoft + OpenRouter free vision) — vision на OpenRouter :free (Qwen3 VL 235B). Лимит 1000 RPD при $10+ deposit покрывает 150 vision/день с запасом. Риск: free может отвалиться.
A23: S3 (pay-as-you-go) — все потоки через Polza.ai или VseLLM на дешёвых моделях. Без подписок. Гибко, но без предсказуемости.
A24: S4 (Гибрид, рекомендуется) — Wormsoft Simple держит текст + embed; vision: 30% через GigaChat-2-Pro (premium источники), 70% через OpenRouter :free; средняя 150₽/1M.
A25: Vision-цены включают image input tokens (~2000/картинку для GigaChat).
A26: Embed для S0/S2/S4 = 0 (внутри Wormsoft Simple); для S1/S3 — отдельная плата 50₽/1M.

Sheet Routing
A1: Стратегия маршрутизации (S4 Гибрид)
A3: Задача | B3: Primary | C3: Fallback 1 | D3: Fallback 2 | E3: Триггер fallback | F3: Комментарий
A4: relevance_concepts | B4: Wormsoft / wormsoft/agent/medium | C4: GigaChat-2-Pro | D4: OpenRouter DeepSeek R1 :free | E4: 429, latency >5s | F4: Joint вызов экономит ~30% vs split. Уже есть в admin/llm_routing.
A5: valence | B5: Wormsoft / wormsoft/agent/small | C5: GigaChat-2 | D5: OpenRouter Llama 3.3 70B :free | E5: 429 | F5: Лёгкая задача, OK на free
A6: concepts (split) | B6: Wormsoft / wormsoft/agent/medium | C6: GigaChat-2-Pro | D6: Polza.ai Qwen-Plus | E6: 429 | F6: Только если RC_JOINT отключен
A7: mcp_synthesis | B7: Wormsoft / wormsoft/agent/large | C7: GigaChat-2-Pro | D7: Polza.ai Claude Haiku | E7: Качество ниже порога | F7: Синтез ответов в Claude-проектах
A8: missing_signals | B8: Wormsoft / wormsoft/agent/medium | C8: OpenRouter DeepSeek R1 :free | D8: — | E8: 429 | F8: Поисковые подсказки, нечастые
A9: embed | B9: Wormsoft / qwen/qwen3-embedding:8b | C9: GigaChat EmbeddingsGigaR | D9: — | E9: Ошибка размерности | F9: Реиндекс при смене (EMBED_DIM)
A10: vision (premium 30%) | B10: GigaChat-2-Pro Vision | C10: Polza.ai GigaChat-2-Pro | D10: OpenRouter Qwen3 VL :free | E10: Источники с quality_tier=trusted | F10: Сохраняем качество для TechCrunch/WIRED
A11: vision (mass 70%) | B11: OpenRouter Qwen3 VL 235B :free | C11: OpenRouter Qwen3.6 Plus :free | D11: GigaChat-2-Pro | E11: 429 / 5xx | F11: Допустима небольшая просадка
A14: Где встроено и что докрутить
A15: shared/llm_routing.py уже умеет per-task provider+model+fallback (LLMRoutingSettings). Добавить fallback2_provider/fallback2_model.
A16: worker/llm_router_client.py: добавить адаптер OpenRouter поверх OpenAI-совместимого API. Похоже на wormsoft_client.py (~50-80 строк).
A17: admin/backend/services: создать openrouter_limits.py (счётчик RPD/RPM в Redis — у OR нет remaining endpoint). Бить 429 локально до отправки.
A18: config/enrichment_policy.yml: добавить vision_routing с правилом по quality_tier (trusted → giga_pro, exploratory → openrouter_free).
A19: Метрики Prometheus: фасет provider в llm_request_total / llm_fallback_total для openrouter.
A20: Алерты: OpenRouter 429 burst > 50/час → runtime override через RUNTIME_LLM_ROUTING_REDIS_KEY переключает primary на GigaChat Pro.

Sheet Free risks
A1: OpenRouter :free — реалии и риски
A3: Параметр | B3: Значение | C3: Что это значит для нас
A4: RPD без депозита | B4: 50/день | C4: Бесполезно для прода
A5: RPD при $10+ депозите | B5: 1000/день | C5: Покрывает 30k запросов/мес — достаточно для vision (5k/мес) с запасом
A6: RPM | B6: 20/мин | C6: При burst 500 vision/час — нужен throttle на нашей стороне
A7: Failed attempts | B7: Считаются в RPD | C7: Учитывать в счётчике, иначе 5xx-цикл съест бюджет
A8: Free preview status | B8: Может закончиться без warning | C8: Мониторить /api/v1/models раз в час
A9: Shared capacity | B9: Throttle при peak | C9: Latency может скакать до 30+ сек
A10: Embeddings | B10: НЕТ free embeddings | C10: Embed остаётся на Wormsoft qwen или GigaChat
A11: Vision quality | B11: Qwen3 VL 235B ~ GigaChat Pro | C11: OK для массовых; для trusted — Giga Pro
A12: Privacy / ToS | B12: Запросы могут логироваться | C12: Не отправлять чувствительный контент; для публичных постов — ок
A13: Депозит $10 ≈ 900₽ | B13: Единоразово | C13: Окупается за 1 мес. Не «кредит на запросы», только разблокирует 1000 RPD
